README
setup.cfg
setup.py
boo_box/__init__.py
boo_box/affiliates.py
boo_box/boo_box.py
boo_box.egg-info/PKG-INFO
boo_box.egg-info/SOURCES.txt
boo_box.egg-info/dependency_links.txt
boo_box.egg-info/entry_points.txt
boo_box.egg-info/paster_plugins.txt
boo_box.egg-info/top_level.txt
boo_box.egg-info/zip-safe
