Metadata-Version: 1.0
Name: boo-box
Version: 0.3.6
Summary: Boo-Box to monetize
Home-page: http://www.assembla.com/spaces/py_boo_box
Author: Walter Cruz
Author-email: walter@waltercruz.com
License: GPL
Platform: UNKNOWN
Classifier: Intended Audience :: Developers
Classifier: Development Status :: 4 - Beta
Classifier: License :: OSI Approved :: GNU General Public License (GPL)
Classifier: Programming Language :: Python
